{
  "title": "Очередь RabbitMQ",
  "uid": "rabbitmq",
  "schemaVersion": 39,
  "version": 1,
  "editable": true,
  "time": {
    "from": "now-1h",
    "to": "now"
  },
  "timezone": "",
  "refresh": "15s",
  "templating": {
    "list": []
  },
  "annotations": {
    "list": []
  },
  "panels": [
    {
      "id": 1,
      "type": "stat",
      "title": "Готовы к доставке",
      "datasource": {
        "type": "prometheus",
        "uid": "prometheus"
      },
      "gridPos": {
        "x": 0,
        "y": 0,
        "w": 6,
        "h": 4
      },
      "targets": [
        {
          "refId": "A",
          "datasource": {
            "type": "prometheus",
            "uid": "prometheus"
          },
          "expr": "rabbitmq_queue_messages_ready",
          "instant": true,
          "range": false
        }
      ],
      "fieldConfig": {
        "defaults": {
          "unit": "short"
        },
        "overrides": []
      },
      "options": {
        "reduceOptions": {
          "calcs": [
            "lastNotNull"
          ],
          "fields": "",
          "values": false
        },
        "orientation": "auto",
        "colorMode": "value",
        "graphMode": "area",
        "textMode": "value_and_name"
      }
    },
    {
      "id": 2,
      "type": "stat",
      "title": "В обработке (unacked)",
      "datasource": {
        "type": "prometheus",
        "uid": "prometheus"
      },
      "gridPos": {
        "x": 6,
        "y": 0,
        "w": 6,
        "h": 4
      },
      "targets": [
        {
          "refId": "A",
          "datasource": {
            "type": "prometheus",
            "uid": "prometheus"
          },
          "expr": "rabbitmq_queue_messages_unacked",
          "instant": true,
          "range": false
        }
      ],
      "fieldConfig": {
        "defaults": {
          "unit": "short"
        },
        "overrides": []
      },
      "options": {
        "reduceOptions": {
          "calcs": [
            "lastNotNull"
          ],
          "fields": "",
          "values": false
        },
        "orientation": "auto",
        "colorMode": "value",
        "graphMode": "area",
        "textMode": "value_and_name"
      }
    },
    {
      "id": 3,
      "type": "stat",
      "title": "Соединения",
      "datasource": {
        "type": "prometheus",
        "uid": "prometheus"
      },
      "gridPos": {
        "x": 12,
        "y": 0,
        "w": 6,
        "h": 4
      },
      "targets": [
        {
          "refId": "A",
          "datasource": {
            "type": "prometheus",
            "uid": "prometheus"
          },
          "expr": "rabbitmq_connections",
          "instant": true,
          "range": false
        }
      ],
      "fieldConfig": {
        "defaults": {
          "unit": "short"
        },
        "overrides": []
      },
      "options": {
        "reduceOptions": {
          "calcs": [
            "lastNotNull"
          ],
          "fields": "",
          "values": false
        },
        "orientation": "auto",
        "colorMode": "value",
        "graphMode": "area",
        "textMode": "value_and_name"
      }
    },
    {
      "id": 4,
      "type": "stat",
      "title": "Потребители",
      "datasource": {
        "type": "prometheus",
        "uid": "prometheus"
      },
      "gridPos": {
        "x": 18,
        "y": 0,
        "w": 6,
        "h": 4
      },
      "targets": [
        {
          "refId": "A",
          "datasource": {
            "type": "prometheus",
            "uid": "prometheus"
          },
          "expr": "rabbitmq_consumers",
          "instant": true,
          "range": false
        }
      ],
      "fieldConfig": {
        "defaults": {
          "unit": "short"
        },
        "overrides": []
      },
      "options": {
        "reduceOptions": {
          "calcs": [
            "lastNotNull"
          ],
          "fields": "",
          "values": false
        },
        "orientation": "auto",
        "colorMode": "value",
        "graphMode": "area",
        "textMode": "value_and_name"
      }
    },
    {
      "id": 5,
      "type": "timeseries",
      "title": "Сообщения в очереди",
      "datasource": {
        "type": "prometheus",
        "uid": "prometheus"
      },
      "gridPos": {
        "x": 0,
        "y": 4,
        "w": 12,
        "h": 8
      },
      "targets": [
        {
          "refId": "A",
          "datasource": {
            "type": "prometheus",
            "uid": "prometheus"
          },
          "expr": "rabbitmq_queue_messages_ready",
          "instant": false,
          "range": true,
          "legendFormat": "готовы"
        },
        {
          "refId": "B",
          "datasource": {
            "type": "prometheus",
            "uid": "prometheus"
          },
          "expr": "rabbitmq_queue_messages_unacked",
          "instant": false,
          "range": true,
          "legendFormat": "в обработке"
        }
      ],
      "fieldConfig": {
        "defaults": {
          "unit": "short",
          "custom": {
            "drawStyle": "line",
            "lineWidth": 1,
            "fillOpacity": 10,
            "showPoints": "never"
          }
        },
        "overrides": []
      },
      "options": {
        "legend": {
          "displayMode": "list",
          "placement": "bottom",
          "showLegend": true
        },
        "tooltip": {
          "mode": "multi",
          "sort": "desc"
        }
      }
    },
    {
      "id": 6,
      "type": "timeseries",
      "title": "Публикация и доставка, /с",
      "datasource": {
        "type": "prometheus",
        "uid": "prometheus"
      },
      "gridPos": {
        "x": 12,
        "y": 4,
        "w": 12,
        "h": 8
      },
      "targets": [
        {
          "refId": "A",
          "datasource": {
            "type": "prometheus",
            "uid": "prometheus"
          },
          "expr": "sum(rate(rabbitmq_channel_messages_published_total[5m]))",
          "instant": false,
          "range": true,
          "legendFormat": "публикация"
        },
        {
          "refId": "B",
          "datasource": {
            "type": "prometheus",
            "uid": "prometheus"
          },
          "expr": "sum(rate(rabbitmq_channel_messages_delivered_total[5m]))",
          "instant": false,
          "range": true,
          "legendFormat": "доставка"
        }
      ],
      "fieldConfig": {
        "defaults": {
          "unit": "short",
          "custom": {
            "drawStyle": "line",
            "lineWidth": 1,
            "fillOpacity": 10,
            "showPoints": "never"
          }
        },
        "overrides": []
      },
      "options": {
        "legend": {
          "displayMode": "list",
          "placement": "bottom",
          "showLegend": true
        },
        "tooltip": {
          "mode": "multi",
          "sort": "desc"
        }
      }
    }
  ]
}